dbt_redshift_dryrun/__init__.py
dbt_redshift_dryrun/app.py
dbt_redshift_dryrun/dryrun.py
dbt_redshift_dryrun-0.10.1.dist-info/LICENSE
dbt_redshift_dryrun-0.10.1.dist-info/METADATA
dbt_redshift_dryrun-0.10.1.dist-info/WHEEL
dbt_redshift_dryrun-0.10.1.dist-info/entry_points.txt
dbt_redshift_dryrun-0.10.1.dist-info/top_level.txt
dbt_redshift_dryrun-0.10.1.dist-info/RECORD
