Metadata-Version: 2.1
Name: dbt_redshift_dryrun
Version: 0.10.1
Summary: Python package dry running redshift queries
Home-page: https://github.com/shassaan/dbt-redshift-dryrun
Author: Syed Hassaan Ahmed
Author-email: syedhassaan.103@gmail.com
License: BSD 2-clause
Classifier: Development Status :: 1 - Planning
Classifier: Intended Audience :: Science/Research
Classifier: License :: OSI Approved :: BSD License
Classifier: Operating System :: POSIX :: Linux
Classifier: Programming Language :: Python :: 2
Classifier: Programming Language :: Python :: 2.7
Classifier: Programming Language :: Python :: 3
Classifier: Programming Language :: Python :: 3.4
Classifier: Programming Language :: Python :: 3.5
License-File: LICENSE
